Workbook

Sheet Benchmarks
A1: Category | B1: Benchmark
A2: Margin | B2: 0.7
A3: Shared Services | B3: 0.045
A4: Executive team | B4: 0.045
A5: Sales | B5: 0.05
A6: Marketing | B6: 0.01
A7: Technical Support | B7: 0.02
A8: Hosting | B8: 0.01
A9: Product | B9: 0.02
A10: Engineering | B10: 0.1
A11: Expense Total | B11: =sum(B3:B10) -> 0.3

Sheet P&L Summary
A1: P&L Summary | B1: 2018 Total
A2: Revenue | B2: =sum(B3:B5) -> 79194484
A3: Recurring | B3: =sum(RecurringRevenue!D4:D2115) -> 68584167
A4: PSO | B4: =sum(PSORevenue!D4:D326) -> 9307488.2
A5: Perpetual | B5: =sum(PerpetualRevenue!D4:D87) -> 1302828.3
A8: HC Expense (W2) | B8: =sum(Empl.!G4:G461) -> 30544906
A9: Non HC Expense (COGS) | B9: =sum('COGS - NEmpl.'!F3:F851) -> 14461558
A10: Non HC Expense (OPEX) | B10: =sum('OPEX - NEmpl.'!F3:F1892) -> 27170630
A11: Non HC Expense - TOTAL | B11: =B9+B10 -> 41632187
A12: Expense | B12: =B8+B11 -> 72177093
A13: Margin | B13: =B2-B12 -> 7017390.5
A14: Margin % | B14: =B13/B2 -> 0.088609587
A16: Expense Breakdown
A17: Cost of Product | B17: =B26+B35 -> 18139886
A18: CloudOps | B18: =B27+B36 -> 9986932.2
A19: Cost of PSO | B19: =B28+B37 -> 7072600.6
A20: G&A | B20: =B29+B38 -> 15772901
A21: R&D | B21: =B30+B39 -> 17285457
A22: S&M | B22: =B31+B40 -> 13906248
A23: Total Expenses | B23: =B17+sum(B19:B22) -> 72177093
A25: Employee Expense Breakdown
A26: =A17 -> Cost of Product | B26: =sumif(Empl.!$D$4:$D$461, $A26, Empl.!$G$4:$G$461) -> 6553936.4
A27: CloudOps | B27: =sumif(Empl.!$E$4:$E$461, "Cloud Operations", Empl.!$G$4:$G$461) -> 1638920.8
A28: =A19 -> Cost of PSO | B28: =sumif(Empl.!$D$4:$D$461, $A28, Empl.!$G$4:$G$461) -> 4196992.8
A29: =A20 -> G&A | B29: =sumif(Empl.!$D$4:$D$461, $A29, Empl.!$G$4:$G$461) -> 6514516.8
A30: =A21 -> R&D | B30: =sumif(Empl.!$D$4:$D$461, $A30, Empl.!$G$4:$G$461) -> 9023520
A31: =A22 -> S&M | B31: =sumif(Empl.!$D$4:$D$461, $A31, Empl.!$G$4:$G$461) -> 4255939.6
A32: Total | B32: =B26+sum(B28:B31) -> 30544906
A34: Non Employee (COGS) Breakdown
A35: =A26 -> Cost of Product | B35: =sumif('COGS - NEmpl.'!$B$3:$B$851, $A35, 'COGS - NEmpl.'!$F$3:$F$851) -> 11585950
A36: CloudOps | B36: =sumif('COGS - NEmpl.'!$C$3:$C$851, "Cloud Operations", 'COGS - NEmpl.'!$F$3:$F$851) -> 8348011.4
A37: =A28 -> Cost of PSO | B37: =sumif('COGS - NEmpl.'!$B$3:$B$851, $A37, 'COGS - NEmpl.'!$F$3:$F$851) -> 2875607.8
A38: =A29 -> G&A | B38: =sumif('OPEX - NEmpl.'!$B$3:$B$1892, $A38, 'OPEX - NEmpl.'!$F$3:$F$1892) -> 9258384.3
A39: =A30 -> R&D | B39: =sumif('OPEX - NEmpl.'!$B$3:$B$1892, $A39, 'OPEX - NEmpl.'!$F$3:$F$1892) -> 8261937.3
A40: =A31 -> S&M | B40: =sumif('OPEX - NEmpl.'!$B$3:$B$1892, $A40, 'OPEX - NEmpl.'!$F$3:$F$1892) -> 9650307.9
A41: Total | B41: =B35+sum(B37:B40) -> 41632187
A45: Expense Check | B45: =B23-B12 -> -5.9604645e-08
A46: HC Check | B46: =B32-B8 -> 7.4505806e-09
A47: NHC Check | B47: =B41-B11 -> -6.7055225e-08

Sheet OPEX - NEmpl.
A1: IN USD
A2: Function L1 | B2: Function L2 | C2: Dept | D2: Dept | E2: Vendor | F2: 2018 total
A3: OPEX | B3: G&A | C3: Corporate Technology | D3: Hosting | F3: 7050
A4: OPEX | B4: G&A | C4: Enterprise Systems | D4: Hosting | F4: 0
A5: OPEX | B5: G&A | C5: Enterprise Systems | D5: T&E/Other | F5: 0
A6: OPEX | B6: G&A | C6: Finance & Accounting | D6: Outsourced Services | F6: 1410
A7: OPEX | B7: G&A | C7: Finance & Accounting | D7: Outsourced Services | F7: 282
A8: OPEX | B8: G&A | C8: Finance & Accounting | D8: Outsourced Services | F8: 211.5
A9: OPEX | B9: G&A | C9: Finance & Accounting | D9: Outsourced Services | F9: 117.5
A10: OPEX | B10: G&A | C10: Finance & Accounting | D10: Outsourced Services | F10: 399.5
A11: OPEX | B11: G&A | C11: Finance & Accounting | D11: Outsourced Services | F11: 117.5
A12: OPEX | B12: G&A | C12: G&A | D12: Personnel | F12: -493.5
A13: OPEX | B13: G&A | C13: GMs & Office Admins | D13: Bonus | F13: 0
A14: OPEX | B14: G&A | C14: GMs & Office Admins | D14: Commissions | F14: -7228.6
... A1892: OPEX | B1892: S&M | C1892: Sales | D1892: T&E/Other | F1892: 451.2

Sheet COGS - NEmpl.
A1: IN USD
A2: Function L1 | B2: Function L2 | C2: Dept | D2: Dept | E2: Vendor | F2: 2018 total
A3: COGS | B3: Cost of Product | C3: Cloud Operations | D3: External Contractors | F3: 192210
A4: COGS | B4: Cost of Product | C4: Cloud Operations | D4: External Contractors | F4: 0
A5: COGS | B5: Cost of Product | C5: Cloud Operations | D5: Hosting | F5: 0
A6: COGS | B6: Cost of Product | C6: Cloud Operations | D6: Hosting | F6: 0
A7: COGS | B7: Cost of Product | C7: Cloud Operations | D7: Hosting | F7: 204125.3
A8: COGS | B8: Cost of Product | C8: Cloud Operations | D8: Hosting | F8: 0
A9: COGS | B9: Cost of Product | C9: Cloud Operations | D9: Hosting | F9: 51221.6
A10: COGS | B10: Cost of Product | C10: Cloud Operations | D10: Hosting | F10: 0
A11: COGS | B11: Cost of Product | C11: Cloud Operations | D11: Hosting | F11: 0
A12: COGS | B12: Cost of Product | C12: Cloud Operations | D12: Hosting | F12: 306968.4
A13: COGS | B13: Cost of Product | C13: Cloud Operations | D13: Hosting | F13: 0
A14: COGS | B14: Cost of Product | C14: Cloud Operations | D14: Hosting | F14: 0
... A851: COGS | B851: Cost of PSO | C851: Professional Services | D851: T&E/Other | F851: 3835.6

Sheet Empl.
A2: IN USD
A3: Tier | B3: Category | C3: Function L1 | D3: Function L2 | E3: DEPT | F3: Name | G3: 2018 total
A4: Cost | B4: Personnel | C4: COGS | D4: Cost of Product | E4: Cloud Operations | G4: 15400
A5: Cost | B5: Personnel | C5: COGS | D5: Cost of Product | E5: Cloud Operations | G5: 21560
A6: Cost | B6: Personnel | C6: COGS | D6: Cost of Product | E6: Cloud Operations | G6: 18480
A7: Cost | B7: Personnel | C7: COGS | D7: Cost of Product | E7: Cloud Operations | G7: 110000
A8: Cost | B8: Personnel | C8: COGS | D8: Cost of Product | E8: Cloud Operations | G8: 13921.6
A9: Cost | B9: Personnel | C9: COGS | D9: Cost of Product | E9: Cloud Operations | G9: 46750
A10: Cost | B10: Personnel | C10: COGS | D10: Cost of Product | E10: Cloud Operations | G10: 14000.8
A11: Cost | B11: Personnel | C11: COGS | D11: Cost of Product | E11: Customer Success | G11: 121000
A12: Cost | B12: Personnel | C12: COGS | D12: Cost of Product | E12: Customer Success | G12: 93500
A13: Cost | B13: Personnel | C13: COGS | D13: Cost of Product | E13: Technical Support | G13: 66193.6
A14: Cost | B14: Personnel | C14: COGS | D14: Cost of Product | E14: Technical Support | G14: 103950
A15: Cost | B15: Personnel | C15: COGS | D15: Cost of Product | E15: Technical Support | G15: 88000
... A461: Cost | B461: Personnel | C461: OPEX | D461: S&M | E461: Sales | G461: 60636.4

Sheet RecurringRevenue
A1: IN USD
A3: Tier | B3: Type | C3: Customer Name | D3: 2018 total
A4: Revenue | B4: Recurring | D4: 782392.5
A5: Revenue | B5: Recurring | D5: 656253
A6: Revenue | B6: Recurring | D6: 563175
A7: Revenue | B7: Recurring | D7: 413586
A8: Revenue | B8: Recurring | D8: 378427.5
A9: Revenue | B9: Recurring | D9: 339592.5
A10: Revenue | B10: Recurring | D10: 322600.5
A11: Revenue | B11: Recurring | D11: 309375
A12: Revenue | B12: Recurring | D12: 290682
A13: Revenue | B13: Recurring | D13: 217876.5
A14: Revenue | B14: Recurring | D14: 193230
A15: Revenue | B15: Recurring | D15: 176944.5
... A2115: Revenue | B2115: Recurring | D2115: -107482.5

Sheet PSORevenue
B1: IN USD
B2: Maintenance
A3: Tier | B3: Type | C3: Customer Name | D3: =RecurringRevenue!D3 -> 2018 total
A4: Revenue | B4: PSO | D4: 370764.6
A5: Revenue | B5: PSO | D5: 370350.6
A6: Revenue | B6: PSO | D6: 181313.6
A7: Revenue | B7: PSO | D7: 136247.4
A8: Revenue | B8: PSO | D8: 71231
A9: Revenue | B9: PSO | D9: 40746.8
A10: Revenue | B10: PSO | D10: 33120
A11: Revenue | B11: PSO | D11: 17006.2
A12: Revenue | B12: PSO | D12: 16100
A13: Revenue | B13: PSO | D13: 0
A14: Revenue | B14: PSO | D14: 0
A15: Revenue | B15: PSO | D15: -25622
... A326: Revenue | B326: PSO | D326: -9039

Sheet PerpetualRevenue
B1: IN USD
B2: Perpetual
A3: Tier | B3: Type | C3: Customer Name | D3: =RecurringRevenue!D3 -> 2018 total
A4: Revenue | B4: Perpetual | D4: 89138.1
A5: Revenue | B5: Perpetual | D5: 19409.4
A6: Revenue | B6: Perpetual | D6: 6350.9
A7: Revenue | B7: Perpetual | D7: 922.5
A8: Revenue | B8: Perpetual | D8: 824.1
A9: Revenue | B9: Perpetual | D9: 549.4
A10: Revenue | B10: Perpetual | D10: 0
A11: Revenue | B11: Perpetual | D11: 27113.3
A12: Revenue | B12: Perpetual | D12: 19421.7
A13: Revenue | B13: Perpetual | D13: 15580
A14: Revenue | B14: Perpetual | D14: 13763.7
A15: Revenue | B15: Perpetual | D15: 13587.4
... A87: Revenue | B87: Perpetual | D87: 533
